temperature/__init__.py
temperature/celcius.py
CELICUS-0.1.dist-info/METADATA
CELICUS-0.1.dist-info/WHEEL
CELICUS-0.1.dist-info/top_level.txt
CELICUS-0.1.dist-info/RECORD
