Metadata-Version: 2.1
Name: CELICUS
Version: 0.1
Summary: Convert between Celsius and Fahrenheit easily
Author: James Nithil
Author-email: jamnithil@gmail.com
Classifier: Programming Language :: Python :: 3
Classifier: License :: OSI Approved :: MIT License
